magicurl/__init__.py
magicurl/magicstore.py
magicurl/magicurl.py
magicurl-0.1.2.dist-info/LICENSE
magicurl-0.1.2.dist-info/WHEEL
magicurl-0.1.2.dist-info/METADATA
magicurl-0.1.2.dist-info/RECORD
