Metadata-Version: 2.1
Name: magicurl
Version: 0.1.2
Summary: Small library for managing URL constants
Home-page: https://github.com/ravensiris/magicurl
License: MIT
Author: ravensiris
Author-email: maksymilian.jodlowski@gmail.com
Requires-Python: >=3.9,<4.0
Classifier: Development Status :: 3 - Alpha
Classifier: Intended Audience :: Developers
Classifier: License :: OSI Approved :: MIT License
Classifier: Operating System :: OS Independent
Classifier: Programming Language :: Python :: 3
Classifier: Programming Language :: Python :: 3.10
Classifier: Programming Language :: Python :: 3.9
Classifier: Topic :: Software Development :: Libraries :: Python Modules
Requires-Dist: attrs (>=21.4.0,<22.0.0)
Project-URL: Repository, https://github.com/ravensiris/magicurl
